tcod/ec/__init__.py
tcod/ec/py.typed
tcod/ec/test_ec.py
tcod_ec-2.2.1.dist-info/LICENSE
tcod_ec-2.2.1.dist-info/WHEEL
tcod_ec-2.2.1.dist-info/METADATA
tcod_ec-2.2.1.dist-info/RECORD
