Metadata-Version: 2.1
Name: tcod-ec
Version: 2.2.1
Summary: Entity/Component containers for implementing composition over inheritance.
Author-email: Kyle Benesch <4b796c65+github@gmail.com>
Requires-Python: >=3.8
Classifier: Development Status :: 5 - Production/Stable
Classifier: Intended Audience :: Developers
Classifier: License :: OSI Approved :: MIT License
Classifier: Operating System :: OS Independent
Classifier: Programming Language :: Python :: 3
Classifier: Topic :: Software Development :: Libraries :: Python Modules
Classifier: Typing :: Typed
Requires-Dist: typing-extensions >=4.4.0
Requires-Dist: attrs >=22.2.0 ; extra == "test"
Requires-Dist: pytest>=7.2.0 ; extra == "test"
Requires-Dist: pytest-cov ; extra == "test"
Requires-Dist: mypy >=1.1.1 ; extra == "test"
Project-URL: Changelog, https://github.com/HexDecimal/python-tcod-ec/blob/main/CHANGELOG.md
Project-URL: Documentation, https://python-tcod-ec.readthedocs.io
Project-URL: Home, https://github.com/HexDecimal/python-tcod-ec
Project-URL: Source, https://github.com/HexDecimal/python-tcod-ec
Provides-Extra: test
